MANIFEST.in
README.rst
setup.py
docs/conf.py
docs/index.rst
xbob/__init__.py
xbob.db.maskattack.egg-info/PKG-INFO
xbob.db.maskattack.egg-info/SOURCES.txt
xbob.db.maskattack.egg-info/dependency_links.txt
xbob.db.maskattack.egg-info/entry_points.txt
xbob.db.maskattack.egg-info/namespace_packages.txt
xbob.db.maskattack.egg-info/not-zip-safe
xbob.db.maskattack.egg-info/requires.txt
xbob.db.maskattack.egg-info/top_level.txt
xbob/db/__init__.py
xbob/db/maskattack/__init__.py
xbob/db/maskattack/checkfiles.py
xbob/db/maskattack/create.py
xbob/db/maskattack/db.sql3
xbob/db/maskattack/driver.py
xbob/db/maskattack/dumplist.py
xbob/db/maskattack/models.py
xbob/db/maskattack/query.py
xbob/db/maskattack/test.py