Metadata-Version: 1.1
Name: xbob.db.maskattack
Version: 1.0.0a0
Summary: 3D Mask Attack Database Access API for Bob
Home-page: http://github.com/bioidiap/xbob.db.maskattack
Author: Nesli Erdogmus
Author-email: nesli.erdogmus@idiap.ch
License: GPLv3
Platform: UNKNOWN
Classifier: Development Status :: 5 - Production/Stable
Classifier: Intended Audience :: Science/Research
Classifier: License :: OSI Approved :: GNU General Public License v3 (GPLv3)
Classifier: Natural Language :: English
Classifier: Programming Language :: Python
Classifier: Topic :: Scientific/Engineering :: Artificial Intelligence
Classifier: Topic :: Database :: Front-Ends
